setup.cfg
setup.py
seaborn/__init__.py
seaborn/parse_doc.py
seaborn_parse_doc.egg-info/PKG-INFO
seaborn_parse_doc.egg-info/SOURCES.txt
seaborn_parse_doc.egg-info/dependency_links.txt
seaborn_parse_doc.egg-info/entry_points.txt
seaborn_parse_doc.egg-info/top_level.txt
test/test_parse_doc.py