Metadata-Version: 1.1
Name: seaborn-parse-doc
Version: 0.0.1
Summary: SeabornParseDoc parses the docstringof the calling function, then returnsits components in one of several ways.
Home-page: https://github.com/SeabornGames/ParseDoc
Author: Ben Christenson
Author-email: Python@BenChristenson.com
License: MIT License
Download-URL: https://github.com/SeabornGames/ParseDoc/tarball/download
Keywords: metadata
Platform: UNKNOWN
Classifier: Intended Audience :: Developers
Classifier: Natural Language :: English
Classifier: License :: Other/Proprietary License
Classifier: Operating System :: POSIX :: Linux
Classifier: Programming Language :: Python
Classifier: Programming Language :: Python :: 2.7
Classifier: Programming Language :: Python :: 3.6
